{"url": "https://www.mdpi.com/2311-5521/7/1/16/review_report", "id": "fluids7010016.a11", "original_article_doi": "https://doi.org/10.3390/fluids7010016", "original_article_url": "https://www.mdpi.com/2311-5521/7/1/16/", "type": "author-comment", "round": 1, "replying_to": 1, "supplementary_materials": [{"filename": "fluids7010016.a11.txt", "id": "fluids7010016.a11", "title": "This sub_article in plaintext."}, {"id": "fluids7010016.s11", "filename": "fluids7010016.s11.docx", "type": "author-coverletter", "original_filename": "Author Response.docx", "url": "https://susy.mdpi.com/user/review/displayFile/22558751/XYfL0USC?file=author-coverletter&report=15947136", "title": "Author Response"}]}