{"url": "https://www.mdpi.com/2410-3896/1/1/2/review_report", "id": "condmat1010002.a12", "original_article_doi": "https://doi.org/10.3390/condmat1010002", "original_article_url": "https://www.mdpi.com/2410-3896/1/1/2/", "type": "author-comment", "round": 1, "replying_to": 2, "supplementary_materials": [{"filename": "condmat1010002.a12.txt", "id": "condmat1010002.a12", "title": "This sub_article in plaintext."}, {"id": "condmat1010002.s11", "filename": "condmat1010002.s11.pdf", "type": "author-coverletter", "original_filename": "Author Response.pdf", "url": "https://susy.mdpi.com/user/review/displayFile/2049445/AMqK95eO?file=author-coverletter&report=1282679", "title": "Author Response"}]}